yeonjae_universal_http_api_client/__init__.py
yeonjae_universal_http_api_client/adapters.py
yeonjae_universal_http_api_client/client.py
yeonjae_universal_http_api_client/exceptions.py
yeonjae_universal_http_api_client/models.py
yeonjae_universal_http_api_client/py.typed
yeonjae_universal_http_api_client/utils.py
yeonjae_universal_http_api_client-1.0.5.dist-info/METADATA
yeonjae_universal_http_api_client-1.0.5.dist-info/WHEEL
yeonjae_universal_http_api_client-1.0.5.dist-info/top_level.txt
yeonjae_universal_http_api_client-1.0.5.dist-info/RECORD
